{"cameraMode":{"drawMode":0,"name":"Shaded","section":"Shading Mode"},"sceneLighting":true,"audioPlay":false,"sceneViewState":{"m_AlwaysRefresh":false,"showFog":true,"showSkybox":true,"showFlares":true,"showImageEffects":true,"showParticleSystems":true,"showVisualEffectGraphs":true,"m_FxEnabled":true},"in2DMode":false,"pivot":{"x":-128.7041778564453,"y":16.825990676879884,"z":-4.921670913696289},"rotation":{"x":0.23318292200565339,"y":0.674786388874054,"z":-0.2348318099975586,"w":0.6613638997077942},"size":13.687376022338868,"orthographic":false}